ccnmtlsettings/__init__.py
ccnmtlsettings/compose.py
ccnmtlsettings/docker.py
ccnmtlsettings/production.py
ccnmtlsettings/shared.py
ccnmtlsettings/staging.py
ccnmtlsettings-1.9.5.dist-info/METADATA
ccnmtlsettings-1.9.5.dist-info/WHEEL
ccnmtlsettings-1.9.5.dist-info/top_level.txt
ccnmtlsettings-1.9.5.dist-info/RECORD
