Metadata-Version: 2.1
Name: ccnmtlsettings
Version: 1.9.5
Summary: Columbia CTL common Django base settings
Home-page: https://github.com/ccnmtl/ccnmtlsettings
Author: Anders Pearson
Author-email: ctl-dev@columbia.edu
License: BSD
Platform: any
Requires-Dist: django-compressor
Requires-Dist: django-debug-toolbar
Requires-Dist: coverage
Requires-Dist: django-smoketest
Requires-Dist: django-extensions
Requires-Dist: django-statsd-mozilla
Requires-Dist: sentry-sdk
Requires-Dist: django-markwhat
Requires-Dist: django-storages
Requires-Dist: boto3
Requires-Dist: statsd
Requires-Dist: gunicorn
Requires-Dist: djangowind
Requires-Dist: django-impersonate
